pyledshop/WifiLedShopLight.py
pyledshop/WifiLedShopLightState.py
pyledshop/__init__.py
pyledshop/constants.py
pyledshop/effects.py
pyledshop/utils.py
pyledshop-0.0.2.dist-info/LICENSE
pyledshop-0.0.2.dist-info/METADATA
pyledshop-0.0.2.dist-info/WHEEL
pyledshop-0.0.2.dist-info/top_level.txt
pyledshop-0.0.2.dist-info/RECORD
